{"80KUoXhWFTPrPmNePp623Q==":"anim.png","MBPGjIKgF1EPj2IHX9J6Aw==":"image1.png","twtislR3UuuJDwPGhtQi2A==":"image2.jpg","jCoj1L/dhn2erebrxHYZOw==":"mbr-1920x1280.jpg","fNVlddFOYgFVGYao/0KbEw==":"alanadee-logo.svg","LDHDQZQ3g0mMK76u6ButMg==":"alanadee-logo%20(1000%20%C3%97%201000%20px)%20(1)-1476x1476.png","atUcJVN9e6pGVVTMGr42+A==":"mbr-1920x1008.jpg","g6/OtwRN0O5eh6I+FPvDig==":"mbr-1-1920x1280.jpg","HzHRgu2oMKA8VIrFKdg6Ag==":"mbr-980x720.jpg","rDY6LFJlMt+1vW+Jh4+/rg==":"mbr-980x613.jpg","RD2takQYShp4PgYPy/PzFg==":"mbr-980x653.jpg","4f39qbrpkxWF25xM4yckIw==":"alanadee-logo%20(1000%20%C3%97%201000%20px)%20(1)-1500x1500.png","zKvotww7xuE1yjkjSMOHYA==":"mbr-1920x1277.jpg","Jro/XzQq9GzrFw++ZIfXDA==":"mbr-2-1920x1280.jpg","Dz1Th9bzMIPPduiEOAkCfA==":"man-3.jpg","JiCK7acFiMEBIy2/97TESw==":"logo-jeelan.svg","BryNk5xwBkVJQU6jxulTOA==":"mbr-1920x1279.jpg","tMTTHqMNl3vy7i+MDDHEkQ==":"mbr-1-980x653.jpg","6b/MNR9YyesZMaqU8YPFeg==":"mbr-1-1920x1279.jpg","9nBKZ/c15PIOC00FVdpYoQ==":"mbr-1920x1920.png","sv+gA4Dz11LwlShkSIGV8g==":"mbr-1620x1296.jpg","cM9LeuKeMRJZdCwEw6jWVQ==":"mbr-1-1920x1920.png","dG3RdKodyDAXoM0xlzWQGw==":"mbr-1920x1194.jpg","Eo8AelnP4ags9cLFwl1o+g==":"mbr-1920x1233.png","rRGtd8HRcea12pmF/Y1sqw==":"fulll-logo-jeelan-500x417.png","9mj/lBsR8N3utxGfOFky8g==":"mbr-1920x1920.jpg","7ki2WwELpuJgac9p7szpMg==":"mbr-1920x1200.jpg","eKc0XJEQBUtBQ41bBpK8sA==":"mbr-1920x1275.jpg","obv/7DXqDVr4cVYSrJORfg==":"mbr-3-1920x1280.jpg","BDeyqqsNeZkqRPxtj+iTFA==":"mbr-4-1920x1280.jpg","/CFucyq0sGC6UhfF6N3hrQ==":"pexels-tiger-lily-4483610-2000x1333.jpg","3afdLxxarTnJvWoW2Zievg==":"mbr-1920x1080.png","sTvIDhb7tPrbpITk6E47Eg==":"mbr-5-1920x1280.jpg","MW1obJmR8ByqoJi2GnC6zg==":"sf-logo.svg","S7dTpdRHJq/86+QtJ3fHJw==":"mbr-980x656.jpg","X4g5G/IkPP72Oaoz2xoePw==":"mbr-2-980x653.jpg","AwsuV7YZQThqdYEQUk7W2g==":"mbr-980x551.jpg","mKv5XECEUq/ux/p0paC7mw==":"portx12-650x520.jpg","2vH0G3RXo2oQvLhd0TEaWw==":"portx12-650x520.jpeg","gje0HYGmwx8fr20Ocvg0lg==":"mbr-3-980x653.jpg","jwPikyFDcFbVog/wQDs6Dg==":"mbr-980x614.jpg","RbXtzP5fkr81zYAsrVaJ9A==":"mbr-1920x1281.jpg","qJ3oSvzbxMrApzSh6FK3zw==":"background7.svg","txJCbu9OeBpoqE/6s9DVfg==":"jnklsd.svg","Kwu91oStaaB6wKa3pUCTNQ==":"background3.jpg","iWbjGq2iHhBr2mJmQktsvw==":"background1-1.jpg","NwsXEzhYeCh0iXmyokbkAg==":"mbr-635x610.png","WVOcdvvsha+lYF2RuJb/PA==":"buildings.svg","pKOZOsNYHTqlVFHjWAROig==":"screen%20shot%202022-06-28%20at%2023.12.11-225x230.png","VEqhhxps34Qsql2QXZaWsA==":"lawback-2000x1329.png","KNvbPRtc3stIP2H8RKM7pQ==":"lawghazwa.logo.svg","/TafQRrWUkpfhg+RQMIGeA==":"log3.svg","IOvrnaHYVuB7jQneOUfQ6Q==":"vision-law.svg","mbaySx3gaXTzHq7SobQ51A==":"vision-law1.svg","83S0mYu3qrkuJOk4ReXhCA==":"%D9%86%D9%81%D8%A7%D8%B0-1920x1080.png","NaZT3zCFx0tT6S2DlLw4BQ==":"2.svg","VMyff83NFDzKRgF7VWNU/Q==":"6.svg","9h0NuFJRoZz/RHBdHOrMhg==":"1.svg","bMkacpTfdflBg2r0wE0ZqA==":"3.svg","5ItG/YX9qXiirkSXO+o7hQ==":"4.svg","vdzNdKS5gy9ZC2cxqMk+bQ==":"18.svg","0HWIArWNAmxqi+UNmv8FDg==":"24.svg","iBhU90qtJfByoKQpDqMejQ==":"16.svg","6jZaGphGlzJTmz2dckn4ng==":"13.svg","xjomwFhjtsgxKsWImvuvWg==":"8.svg","d2ll8052xVk7IkFPv/bxJA==":"5.svg","G8qeFogRLwfF/RIbpjOfXQ==":"7.svg","ZGYY/2pkPqDGjy/aC2zjSg==":"19.svg","VXqVYrnDT8JTbkZpisZHyg==":"10.svg","0Kz3HePHDGRTIeQj4OH5EQ==":"15.svg","zDqkYOA3Ek6cdHitKOv5pA==":"11.svg","SsdFrypTpYWUJOppZvnC2Q==":"17.svg","rFx7YJ+yUJPJV66kSlPJhw==":"9.svg","S8bxuMgUTH+TxEDgwkPo5Q==":"14.svg","+CS/nIIS+RhmT2UNGTVxfg==":"23.svg","Vb7GgbMoe0curpGYBParsg==":"background3-1.jpg","QUxHBUrn88zr+jGx6dzVgQ==":"12.svg","O4uoAtW1xCcaS53ocX54XQ==":"icon1.svg","BIT0KPDzDNGJcZnei9h5lw==":"6-1.svg","J1wkoUzoldST8VHbBISVng==":"5-1.svg","ffyXEt107SoWT5iDkXPrmw==":"7-1.svg","SAdMCvuPiFB94R1Ff2efaQ==":"9-1.svg","IyEHR0wfhG+aXuKC3MdXkA==":"8-1.svg"}